wink_sdk_extranet_experiences/__init__.py
wink_sdk_extranet_experiences/api_client.py
wink_sdk_extranet_experiences/api_response.py
wink_sdk_extranet_experiences/configuration.py
wink_sdk_extranet_experiences/exceptions.py
wink_sdk_extranet_experiences/py.typed
wink_sdk_extranet_experiences/rest.py
wink_sdk_extranet_experiences/api/__init__.py
wink_sdk_extranet_experiences/api/activity_api.py
wink_sdk_extranet_experiences/api/attraction_api.py
wink_sdk_extranet_experiences/api/place_api.py
wink_sdk_extranet_experiences/models/__init__.py
wink_sdk_extranet_experiences/models/activity.py
wink_sdk_extranet_experiences/models/address.py
wink_sdk_extranet_experiences/models/address_supplier.py
wink_sdk_extranet_experiences/models/attraction.py
wink_sdk_extranet_experiences/models/attraction_view.py
wink_sdk_extranet_experiences/models/contact.py
wink_sdk_extranet_experiences/models/contact_supplier.py
wink_sdk_extranet_experiences/models/country.py
wink_sdk_extranet_experiences/models/country_lightweight.py
wink_sdk_extranet_experiences/models/country_lightweight_supplier.py
wink_sdk_extranet_experiences/models/country_supplier.py
wink_sdk_extranet_experiences/models/custom_monetary_amount.py
wink_sdk_extranet_experiences/models/dow_pattern_group.py
wink_sdk_extranet_experiences/models/dow_pattern_group_supplier.py
wink_sdk_extranet_experiences/models/generic_error_message.py
wink_sdk_extranet_experiences/models/geo_json_point.py
wink_sdk_extranet_experiences/models/geo_json_point_supplier.py
wink_sdk_extranet_experiences/models/geo_name.py
wink_sdk_extranet_experiences/models/geo_name_lightweight.py
wink_sdk_extranet_experiences/models/geo_name_lightweight_supplier.py
wink_sdk_extranet_experiences/models/geo_name_supplier.py
wink_sdk_extranet_experiences/models/image_attribution.py
wink_sdk_extranet_experiences/models/image_attribution_supplier.py
wink_sdk_extranet_experiences/models/key_value_pair.py
wink_sdk_extranet_experiences/models/key_value_pair_supplier.py
wink_sdk_extranet_experiences-0.0.57.dist-info/licenses/LICENSE
wink_sdk_extranet_experiences-0.0.57.dist-info/METADATA
wink_sdk_extranet_experiences-0.0.57.dist-info/WHEEL
wink_sdk_extranet_experiences-0.0.57.dist-info/top_level.txt
wink_sdk_extranet_experiences-0.0.57.dist-info/RECORD
